LICENSE
MANIFEST.in
README.md
fastwsgi.py
setup.py
setup_libuv.py
fastwsgi/common.c
fastwsgi/common.h
fastwsgi/constants.c
fastwsgi/constants.h
fastwsgi/fastwsgimodule.c
fastwsgi/filewrapper.c
fastwsgi/filewrapper.h
fastwsgi/logx.c
fastwsgi/logx.h
fastwsgi/pyhacks.c
fastwsgi/pyhacks.h
fastwsgi/request.c
fastwsgi/request.h
fastwsgi/server.c
fastwsgi/server.h
fastwsgi/start_response.c
fastwsgi/start_response.h
fastwsgi/xbuf.h
fastwsgi.egg-info/PKG-INFO
fastwsgi.egg-info/SOURCES.txt
fastwsgi.egg-info/dependency_links.txt
fastwsgi.egg-info/entry_points.txt
fastwsgi.egg-info/requires.txt
fastwsgi.egg-info/top_level.txt
libuv/LICENSE
libuv/include/uv.h
libuv/include/uv/aix.h
libuv/include/uv/bsd.h
libuv/include/uv/darwin.h
libuv/include/uv/errno.h
libuv/include/uv/linux.h
libuv/include/uv/os390.h
libuv/include/uv/posix.h
libuv/include/uv/stdint-msvc2008.h
libuv/include/uv/sunos.h
libuv/include/uv/threadpool.h
libuv/include/uv/tree.h
libuv/include/uv/unix.h
libuv/include/uv/version.h
libuv/include/uv/win.h
libuv/src/fs-poll.c
libuv/src/heap-inl.h
libuv/src/idna.c
libuv/src/idna.h
libuv/src/inet.c
libuv/src/queue.h
libuv/src/random.c
libuv/src/strscpy.c
libuv/src/strscpy.h
libuv/src/strtok.c
libuv/src/strtok.h
libuv/src/threadpool.c
libuv/src/timer.c
libuv/src/uv-common.c
libuv/src/uv-common.h
libuv/src/uv-data-getter-setters.c
libuv/src/version.c
libuv/src/unix/aix-common.c
libuv/src/unix/aix.c
libuv/src/unix/async.c
libuv/src/unix/atomic-ops.h
libuv/src/unix/bsd-ifaddrs.c
libuv/src/unix/bsd-proctitle.c
libuv/src/unix/core.c
libuv/src/unix/cygwin.c
libuv/src/unix/darwin-proctitle.c
libuv/src/unix/darwin-stub.h
libuv/src/unix/darwin.c
libuv/src/unix/dl.c
libuv/src/unix/epoll.c
libuv/src/unix/freebsd.c
libuv/src/unix/fs.c
libuv/src/unix/fsevents.c
libuv/src/unix/getaddrinfo.c
libuv/src/unix/getnameinfo.c
libuv/src/unix/haiku.c
libuv/src/unix/hurd.c
libuv/src/unix/ibmi.c
libuv/src/unix/internal.h
libuv/src/unix/kqueue.c
libuv/src/unix/linux-core.c
libuv/src/unix/linux-inotify.c
libuv/src/unix/linux-syscalls.c
libuv/src/unix/linux-syscalls.h
libuv/src/unix/loop-watcher.c
libuv/src/unix/loop.c
libuv/src/unix/netbsd.c
libuv/src/unix/no-fsevents.c
