Metadata-Version: 2.1
Name: fastwsgi
Version: 0.0.9
Summary: An ultra fast WSGI server for Python 3
Home-page: https://github.com/jamesroberts/fastwsgi
Author: James Roberts
Author-email: jamesroberts.dev@gmail.com
License: MIT
Project-URL: Bug Tracker, https://github.com/jamesroberts/fastwsgi/issues
Project-URL: Source, https://github.com/jamesroberts/fastwsgi
Platform: UNKNOWN
Classifier: License :: OSI Approved :: MIT License
Classifier: Operating System :: OS Independent
Classifier: Topic :: Internet :: WWW/HTTP :: WSGI :: Server
Classifier: Programming Language :: Python :: 3
Classifier: Development Status :: 3 - Alpha
Requires-Python: >=3.6
License-File: LICENSE
